snnpy/__init__.py
snnpy/snn.py
snn_reservoir_py-2.0.0.dist-info/METADATA
snn_reservoir_py-2.0.0.dist-info/WHEEL
snn_reservoir_py-2.0.0.dist-info/top_level.txt
snn_reservoir_py-2.0.0.dist-info/RECORD
