Metadata-Version: 2.4
Name: snn_reservoir_py
Version: 2.0.0
Summary: Simulation and analysis of Spiking Neural Networks (SNNs)
Home-page: https://github.com/RuggeroFreddi/snnpy
Author: Ruggero Freddi
Author-email: info@ruggerofreddi.it
License: MIT
Classifier: Programming Language :: Python :: 3
Classifier: License :: OSI Approved :: MIT License
Classifier: Operating System :: OS Independent
Requires-Python: >=3.7
Requires-Dist: numpy<1.27,>=1.22
Requires-Dist: scipy<1.13,>=1.8
Requires-Dist: networkx<3.3,>=2.6
Requires-Dist: pandas<2.3,>=1.3
Requires-Dist: scikit-learn<1.5,>=1.1
Requires-Dist: matplotlib<3.9,>=3.5
Requires-Dist: seaborn<0.13,>=0.11
